README.md
setup.py
pytuna/__init__.py
pytuna/version.py
pytuna.egg-info/PKG-INFO
pytuna.egg-info/SOURCES.txt
pytuna.egg-info/dependency_links.txt
pytuna.egg-info/requires.txt
pytuna.egg-info/top_level.txt