Metadata-Version: 2.1
Name: pytuna
Version: 0.0.1
Summary: Visym Python Tools for Visual Network Tuning
Home-page: https://github.com/visym/pytuna
Author: Visym Labs
Author-email: info@visym.com
License: UNKNOWN
Download-URL: https://github.com/visym/pytuna/archive/0.0.1.tar.gz
Keywords: computer vision machine learning ML CV privacy video image
Platform: UNKNOWN
Classifier: Programming Language :: Python :: 3
Classifier: Operating System :: OS Independent
Classifier: License :: OSI Approved :: MIT License
